npkpy/__init__.py
npkpy/analyse_npk.py
npkpy/common.py
npkpy/main.py
npkpy/npk/__init__.py
npkpy/npk/cnt_architecture_tag.py
npkpy/npk/cnt_basic.py
npkpy/npk/cnt_flag_a.py
npkpy/npk/cnt_flag_b.py
npkpy/npk/cnt_flag_c.py
npkpy/npk/cnt_mpls.py
npkpy/npk/cnt_null_block.py
npkpy/npk/cnt_squasfs_image.py
npkpy/npk/cnt_squashfs_hash_signature.py
npkpy/npk/cnt_zlib_compressed_data.py
npkpy/npk/npk.py
npkpy/npk/npk_constants.py
npkpy/npk/npk_file_basic.py
npkpy/npk/pck_description.py
npkpy/npk/pck_eckcdsa_hash.py
npkpy/npk/pck_header.py
npkpy/npk/pck_multicontainer_header.py
npkpy/npk/pck_multicontainer_list.py
npkpy/npk/pck_preheader.py
npkpy/npk/pck_release_typ.py
npkpy/npk/pck_requirements_header.py
tests/__init__.py
tests/cnt_basic_test.py
tests/cnt_flag_a_test.py
tests/cnt_flag_b_test.py
tests/cnt_flag_c_test.py
tests/cnt_mpls_test.py
tests/cnt_null_block_test.py
tests/cnt_squas_fs_image_test.py
tests/cnt_squash_fs_hash_signature_test.py
tests/cnt_zlib_compressed_data_test.py
tests/common_test.py
tests/constants.py
tests/npk_constants_test.py
tests/npk_file_basic_test.py
tests/npk_parsing_gps_file_test.py
tests/npk_test.py
tests/pck_description_test.py
tests/pck_eckcdsa_hash_test.py
tests/pck_header_test.py
tests/pck_multicontainer_header_test.py
tests/pck_multicontainer_list_test.py
tests/pck_preheader_test.py
tests/pck_release_typ_test.py
tests/pck_requirements_header_test.py
tests_acceptance_test/__init__.py
tests_acceptance_test/acceptance_test.py
tools/__init__.py
tools/download_all_packages.py
tools/download_all_packages_test.py
tools/npkModify_test.py
tools/sections.py
tools/sections_test.py
tools/demo_modify_nkp_packages/__init__.py
tools/demo_modify_nkp_packages/poc_modify_npk.py
npkPy-2021.10.22.15.58.dist-info/LICENSE
npkPy-2021.10.22.15.58.dist-info/METADATA
npkPy-2021.10.22.15.58.dist-info/WHEEL
npkPy-2021.10.22.15.58.dist-info/entry_points.txt
npkPy-2021.10.22.15.58.dist-info/top_level.txt
npkPy-2021.10.22.15.58.dist-info/RECORD
