Metadata-Version: 2.1
Name: npkPy
Version: 2021.10.22.15.58
Summary: npkPy is an unpacker tool for MikroTiks custom npk container format
Home-page: https://github.com/botlabsDev/npkpy
Author: botlabsDev
Author-email: npkPy@botlabs.dev
License: UNKNOWN
Platform: UNKNOWN
Classifier: Programming Language :: Python :: 3.6
Classifier: License :: OSI Approved :: GNU Affero General Public License v3
Classifier: Operating System :: OS Independent
Requires-Python: >=3.6
